QEasyWidgets/__init__.py
QEasyWidgets/Common/Config.py
QEasyWidgets/Common/Icon.py
QEasyWidgets/Common/Language.py
QEasyWidgets/Common/QFunctions.py
QEasyWidgets/Common/QTasks.py
QEasyWidgets/Common/QWorker.py
QEasyWidgets/Common/Signals.py
QEasyWidgets/Common/StyleSheet.py
QEasyWidgets/Common/Theme.py
QEasyWidgets/Common/Translator.py
QEasyWidgets/Common/__init__.py
QEasyWidgets/Components/Bar.py
QEasyWidgets/Components/Browser.py
QEasyWidgets/Components/Button.py
QEasyWidgets/Components/ChatWidget.py
QEasyWidgets/Components/CheckBox.py
QEasyWidgets/Components/ComboBox.py
QEasyWidgets/Components/DockWidget.py
QEasyWidgets/Components/Edit.py
QEasyWidgets/Components/Frame.py
QEasyWidgets/Components/GroupBox.py
QEasyWidgets/Components/Label.py
QEasyWidgets/Components/List.py
QEasyWidgets/Components/Menu.py
QEasyWidgets/Components/Player.py
QEasyWidgets/Components/ProgressBar.py
QEasyWidgets/Components/ScrollArea.py
QEasyWidgets/Components/Slider.py
QEasyWidgets/Components/SpinBox.py
QEasyWidgets/Components/StatusWidget.py
QEasyWidgets/Components/Tab.py
QEasyWidgets/Components/Table.py
QEasyWidgets/Components/ToolBox.py
QEasyWidgets/Components/Tree.py
QEasyWidgets/Components/Widget.py
QEasyWidgets/Components/__init__.py
QEasyWidgets/Resources/Sources.py
QEasyWidgets/Resources/__init__.py
QEasyWidgets/Windows/Dialog.py
QEasyWidgets/Windows/Window.py
QEasyWidgets/Windows/__init__.py
QEasyWidgets/Windows/FramelessWindow/Window_linux.py
QEasyWidgets/Windows/FramelessWindow/Window_win32.py
QEasyWidgets/Windows/FramelessWindow/__init__.py
QEasyWidgets-0.7.8.dist-info/LICENSE
QEasyWidgets-0.7.8.dist-info/METADATA
QEasyWidgets-0.7.8.dist-info/WHEEL
QEasyWidgets-0.7.8.dist-info/top_level.txt
QEasyWidgets-0.7.8.dist-info/RECORD
