Metadata-Version: 2.1
Name: QEasyWidgets
Version: 0.7.8
Summary: A simple widget library based on PySide6
Home-page: https://github.com/Spr-Aachen/QEasyWidgets
Author: Spr_Aachen
Author-email: 2835946988@qq.com
License: GPLv3
Project-URL: Source Code, https://github.com/Spr-Aachen/QEasyWidgets
Project-URL: Bug Tracker, https://github.com/Spr-Aachen/QEasyWidgets/issues
Classifier: Operating System :: OS Independent
Classifier: Programming Language :: Python :: 3
Classifier: License :: OSI Approved :: GNU General Public License v3 (GPLv3)
License-File: LICENSE
Requires-Dist: PySide6 (<=6.8.2.1)
Requires-Dist: darkdetect
Requires-Dist: nvidia-ml-py
Requires-Dist: PyEasyUtils
Requires-Dist: pywin32 ; platform_system == "Windows"
